{"packages/cupertino_icons/assets/CupertinoIcons.ttf":["packages/cupertino_icons/assets/CupertinoIcons.ttf"],"assets/sounds/bass.wav":["assets/sounds/bass.wav"],"assets/sounds/clap_2.wav":["assets/sounds/clap_2.wav"],"assets/sounds/hat_3.wav":["assets/sounds/hat_3.wav"],"assets/sounds/kick_1.wav":["assets/sounds/kick_1.wav"],"assets/sounds/kick_2.wav":["assets/sounds/kick_2.wav"],"assets/sounds/open_hat.wav":["assets/sounds/open_hat.wav"],"assets/sounds/snare_1.wav":["assets/sounds/snare_1.wav"],"assets/sounds/snare_2.wav":["assets/sounds/snare_2.wav"]}